stronger/__init__.py
stronger/breached_password.py
stronger/multi_factor_authetication.py
stronger/password_generation.py
stronger/password_hash.py
stronger/strength_checker.py
stronger/suggest_improvements.py
stronger_password_package-1.0.3.dist-info/LICENSE
stronger_password_package-1.0.3.dist-info/METADATA
stronger_password_package-1.0.3.dist-info/WHEEL
stronger_password_package-1.0.3.dist-info/top_level.txt
stronger_password_package-1.0.3.dist-info/RECORD
