Metadata-Version: 2.1
Name: stronger-password-package
Version: 1.0.3
Summary: A package for password security
Home-page: https://github.com/Beny16112000/Stronger
Author: Benjamin Shtainberg
Author-email: benny132001@gmail.com
Project-URL: Bug Tracker, https://github.com/Beny16112000/Stronger/issues
Classifier: Programming Language :: Python :: 3
Classifier: License :: OSI Approved :: MIT License
Classifier: Operating System :: OS Independent
Requires-Python: >=3.6
License-File: LICENSE
Requires-Dist: pyotp
Requires-Dist: requests
